interzoid_full_name_match_score/__init__.py
interzoid_full_name_match_score/full_name_match_score.py
interzoid_full_name_match_score-1.0.1.dist-info/METADATA
interzoid_full_name_match_score-1.0.1.dist-info/WHEEL
interzoid_full_name_match_score-1.0.1.dist-info/licenses/LICENSE
interzoid_full_name_match_score-1.0.1.dist-info/RECORD
