Metadata-Version: 2.1
Name: interzoid_full_name_match_score
Version: 1.0.1
Summary: Provides an AI-based match score as to how likely two person names are the same.
Project-URL: Homepage, https://www.interzoid.com/apis/individual-match-score
Author-email: Interzoid <support@interzoid.com>
License-File: LICENSE
Classifier: License :: OSI Approved :: MIT License
Classifier: Operating System :: OS Independent
Classifier: Programming Language :: Python :: 3
Classifier: Topic :: Database
Classifier: Topic :: Scientific/Engineering :: Artificial Intelligence
Requires-Python: >=3.7
